hyperarrow/__init__.py
hyperarrow/_tester.py
hyperarrow/libhyperarrow.cp39-win_amd64.pyd
hyperarrow/tests/__init__.py
hyperarrow/tests/conftest.py
hyperarrow/tests/test_exceptions.py
hyperarrow/tests/test_roundtrip.py
hyperarrow-0.0.1.dev0.data/data/README.md
hyperarrow.libs/.load-order-hyperarrow-0.0.1.dev0
hyperarrow.libs/arrow-0b6e9124.dll
hyperarrow.libs/arrow_python-4ef7844f.dll
hyperarrow.libs/concrt140.dll
hyperarrow.libs/hyperarrow_reader-ac21c1cc.dll
hyperarrow.libs/hyperarrow_writer-e4d4a1fb.dll
hyperarrow.libs/msvcp140.dll
hyperarrow.libs/re2-e6e54597.dll
hyperarrow.libs/tableauhyperapi-eee5a817.dll
hyperarrow.libs/utf8proc-9cd507b2.dll
hyperarrow.libs/hyper/crashdumper.exe
hyperarrow.libs/hyper/hyperd.exe
hyperarrow-0.0.1.dev0.dist-info/DELVEWHEEL
hyperarrow-0.0.1.dev0.dist-info/LICENSE
hyperarrow-0.0.1.dev0.dist-info/METADATA
hyperarrow-0.0.1.dev0.dist-info/WHEEL
hyperarrow-0.0.1.dev0.dist-info/top_level.txt
hyperarrow-0.0.1.dev0.dist-info/RECORD
