Metadata-Version: 2.1
Name: hyperarrow
Version: 0.0.1.dev0
Summary: Python wrapper to hyperarrow
Home-page: https://github.com/innobi/hyperarrow
Author: Will Ayd
Author-email: will_ayd@innobi.io
License: Apache
Keywords: tableau tableauhyperapi arrow
Platform: UNKNOWN
Classifier: Development Status :: 3 - Alpha
Classifier: Intended Audience :: Developers
Classifier: Topic :: Software Development :: Build Tools
Classifier: License :: OSI Approved :: Apache Software License
Classifier: Programming Language :: Python :: 3.8
Classifier: Programming Language :: Python :: 3.9
Classifier: Programming Language :: Python :: 3.10
Requires-Python: >=3.8
License-File: LICENSE
Requires-Dist: pyarrow
Provides-Extra: dev
Requires-Dist: pytest ; extra == 'dev'
